how2write/__init__.py
how2write/main.py
how2write-0.1.2.dist-info/LICENSE
how2write-0.1.2.dist-info/METADATA
how2write-0.1.2.dist-info/WHEEL
how2write-0.1.2.dist-info/entry_points.txt
how2write-0.1.2.dist-info/top_level.txt
how2write-0.1.2.dist-info/RECORD
