Metadata-Version: 2.1
Name: how2write
Version: 0.1.2
Summary: An english-learning helper
Home-page: https://github.com/ChristophePRAT/How2Write
Author: Christophe Prat
Author-email: christopheprat@icloud.com
License: MIT
Platform: UNKNOWN
Classifier: Development Status :: 2 - Pre-Alpha
Classifier: License :: OSI Approved :: MIT License
Classifier: Programming Language :: Python
Classifier: Programming Language :: Python :: 3.6
Classifier: Programming Language :: Python :: 3.7
License-File: LICENSE
Requires-Dist: requests
Requires-Dist: gTTS
Requires-Dist: pygame
